empanada/__init__.py
empanada/_version.py
empanada/array_utils.py
empanada/config_loaders.py
empanada/consensus.py
empanada/losses.py
empanada/metrics.py
empanada/zarr_utils.py
empanada/data/__init__.py
empanada/data/_base.py
empanada/data/bc_dataset.py
empanada/data/panoptic_dataset.py
empanada/data/single_class_instance_dataset.py
empanada/data/volume_dataset.py
empanada/data/utils/__init__.py
empanada/data/utils/sampler.py
empanada/data/utils/target_creation.py
empanada/data/utils/transforms.py
empanada/evaluation/__init__.py
empanada/evaluation/evaluator.py
empanada/evaluation/instance_metrics.py
empanada/evaluation/panoptic_metrics.py
empanada/evaluation/semantic_metrics.py
empanada/inference/__init__.py
empanada/inference/engines.py
empanada/inference/filters.py
empanada/inference/matcher.py
empanada/inference/patterns.py
empanada/inference/postprocess.py
empanada/inference/rle.py
empanada/inference/tile.py
empanada/inference/tracker.py
empanada/inference/watershed.py
empanada/models/__init__.py
empanada/models/blocks.py
empanada/models/heads.py
empanada/models/panoptic_bifpn.py
empanada/models/panoptic_deeplab.py
empanada/models/point_rend.py
empanada/models/decoders/__init__.py
empanada/models/decoders/aspp.py
empanada/models/decoders/bifpn.py
empanada/models/decoders/panoptic_deeplab.py
empanada/models/encoders/__init__.py
empanada/models/encoders/regnet.py
empanada/models/encoders/resnet.py
empanada/models/quantization/__init__.py
empanada/models/quantization/panoptic_bifpn.py
empanada/models/quantization/panoptic_deeplab.py
empanada/models/quantization/point_rend.py
empanada/models/quantization/decoders/__init__.py
empanada/models/quantization/decoders/panoptic_deeplab.py
empanada/models/quantization/encoders/__init__.py
empanada/models/quantization/encoders/regnet.py
empanada/models/quantization/encoders/resnet.py
empanada_napari/__init__.py
empanada_napari/_accuracy_metrics.py
empanada_napari/_create_tiles.py
empanada_napari/_export_batch_segs.py
empanada_napari-1.2.1.dist-info/licenses/LICENSE
empanada_napari-1.2.1.dist-info/METADATA
empanada_napari-1.2.1.dist-info/WHEEL
empanada_napari-1.2.1.dist-info/entry_points.txt
empanada_napari-1.2.1.dist-info/top_level.txt
empanada_napari-1.2.1.dist-info/RECORD
