Metadata-Version: 2.4
Name: empanada-napari
Version: 1.2.1
Summary: Napari plugin of algorithms for Panoptic Segmentation of organelles in EM
Home-page: https://github.com/volume-em/empanada-napari
Author: Abhishek Bhardwaj, Ryan Conrad, Madeline Barry, Kedar Narayan
Author-email: abhishek.bhardwaj@nih.gov
License: BSD-3-Clause
Project-URL: Bug Tracker, https://github.com/volume-em/empanada-napari/issues
Project-URL: Documentation, https://github.com/volume-em/empanada-napari#README.md
Project-URL: Source Code, https://github.com/volume-em/empanada-napari
Project-URL: User Support, https://github.com/volume-em/empanada-napari/issues
Classifier: Development Status :: 2 - Pre-Alpha
Classifier: Intended Audience :: Developers
Classifier: Framework :: napari
Classifier: Topic :: Software Development :: Testing
Classifier: Programming Language :: Python
Classifier: Programming Language :: Python :: 3
Classifier: Programming Language :: Python :: 3.7
Classifier: Programming Language :: Python :: 3.8
Classifier: Programming Language :: Python :: 3.9
Classifier: Operating System :: OS Independent
Classifier: License :: OSI Approved :: BSD License
Requires-Python: >=3.7
License-File: LICENSE
Requires-Dist: torch>=1.10
Requires-Dist: torchvision>=0.2
Requires-Dist: zarr>=2.12
Requires-Dist: albumentations>=1.2
Requires-Dist: pyyaml
Requires-Dist: cztile==1.0.0
Requires-Dist: mlflow
Requires-Dist: opencv-python==4.9.0.80
Requires-Dist: opencv-python-headless==4.9.0.80
Requires-Dist: napari==0.4.18
Requires-Dist: numpy==1.22
Requires-Dist: napari-plugin-engine>=0.1.4
Requires-Dist: scikit-image>=0.19
Requires-Dist: numba==0.58.1
Requires-Dist: imagecodecs
Requires-Dist: openpyxl
Requires-Dist: imagehash
Requires-Dist: mlflow
Requires-Dist: simpleitk
Requires-Dist: tqdm
Dynamic: license-file
